pyhoma/__init__.py
pyhoma/client.py
pyhoma/const.py
pyhoma/enums/__init__.py
pyhoma/enums/command.py
pyhoma/enums/execution.py
pyhoma/enums/gateway.py
pyhoma/enums/general.py
pyhoma/enums/state.py
pyhoma/enums/ui.py
pyhoma/exceptions.py
pyhoma/models.py
pyhoma-0.7.4.dist-info/LICENSE
pyhoma-0.7.4.dist-info/WHEEL
pyhoma-0.7.4.dist-info/METADATA
pyhoma-0.7.4.dist-info/RECORD
