Metadata-Version: 2.1
Name: pyhoma
Version: 0.7.4
Summary: (deprecated, use pyoverkiz instead). Async Python wrapper to interact with internal Somfy TaHoma API, or other OverKiz API's.
Home-page: https://github.com/iMicknl/python-tahoma-api
License: MIT
Author: Mick Vleeshouwer
Requires-Python: >=3.7,<4.0
Classifier: License :: OSI Approved :: MIT License
Classifier: Programming Language :: Python :: 3
Classifier: Programming Language :: Python :: 3.10
Classifier: Programming Language :: Python :: 3.7
Classifier: Programming Language :: Python :: 3.8
Classifier: Programming Language :: Python :: 3.9
Requires-Dist: aiohttp (>=3.6.1,<4.0.0)
Requires-Dist: attrs (>=21.2.0,<22.0.0)
Requires-Dist: backoff (>=1.10.0,<2.0.0)
Requires-Dist: boto3 (>=1.18.59,<2.0.0)
Requires-Dist: pyhumps (>=3.0.2,<4.0.0)
Requires-Dist: warrant (>=0.6.1,<0.7.0)
Project-URL: Repository, https://github.com/iMicknl/python-tahoma-api
